MolGen/ClustEn.py
MolGen/CrystalUtils.py
MolGen/DimReduction.py
MolGen/FeatureSelector.py
MolGen/MolGens.py
MolGen/PlotUtils.py
MolGen/PrepStatic.py
MolGen/__init__.py
MolGen/calc_mats.py
MolGen/cryst_utils.py
MolGen/definitions.py
MolGen/nucleic.py
MolGen/pdbfix.py
MolGen-0.1.dist-info/LICENSE
MolGen-0.1.dist-info/METADATA
MolGen-0.1.dist-info/WHEEL
MolGen-0.1.dist-info/top_level.txt
MolGen-0.1.dist-info/RECORD
