Metadata-Version: 2.1
Name: MolGen
Version: 0.1
Summary: A Molecular Generation Framework package
Author: Your Name
Author-email: vinaysanjay.chaudhari@slu.edu
Classifier: Development Status :: 3 - Alpha
Classifier: Intended Audience :: Science/Research
Classifier: License :: OSI Approved :: MIT License
Classifier: Programming Language :: Python :: 3.7
License-File: LICENSE
Requires-Dist: absl-py ==2.1.0
Requires-Dist: alembic ==1.8.1
Requires-Dist: anyio ==3.5.0
Requires-Dist: argon2-cffi ==21.3.0
Requires-Dist: argon2-cffi-bindings ==21.2.0
Requires-Dist: astunparse ==1.6.3
Requires-Dist: async-generator ==1.10
Requires-Dist: attrs ==21.4.0
Requires-Dist: babel ==2.11.0
Requires-Dist: backcall ==0.2.0
Requires-Dist: barnaba ==0.1.9
Requires-Dist: beautifulsoup4 ==4.12.3
Requires-Dist: bhmm ==0.6.3
Requires-Dist: biopython ==1.78
Requires-Dist: bleach ==4.1.0
Requires-Dist: blinker ==1.4
Requires-Dist: bottleneck ==1.3.5
Requires-Dist: brotli ==1.0.9
Requires-Dist: brotli-bin ==1.0.9
Requires-Dist: brotlipy ==0.7.0
Requires-Dist: cffi ==1.15.1
Requires-Dist: charset-normalizer ==2.0.4
Requires-Dist: contextvars ==2.4
Requires-Dist: cryptography ==39.0.1
Requires-Dist: cycler ==0.11.0
Requires-Dist: debugpy ==1.5.1
Requires-Dist: decorator ==5.1.1
Requires-Dist: deeptime ==0.4.3
Requires-Dist: defusedxml ==0.7.1
Requires-Dist: dill ==0.3.7
Requires-Dist: entrypoints ==0.4
Requires-Dist: flatbuffers ==24.3.7
Requires-Dist: flit-core ==3.6.0
Requires-Dist: fonttools ==4.25.0
Requires-Dist: future ==1.0.0
Requires-Dist: gast ==0.4.0
Requires-Dist: giflib ==5.2.1
Requires-Dist: google-auth ==2.28.2
Requires-Dist: google-auth-oauthlib ==0.4.6
Requires-Dist: google-pasta ==0.2.0
Requires-Dist: greenlet ==2.0.1
Requires-Dist: grpcio ==1.62.1
Requires-Dist: h5py ==3.7.0
Requires-Dist: humanfriendly ==10.0
Requires-Dist: idna ==3.4
Requires-Dist: immutables ==0.16
Requires-Dist: importlib-metadata ==4.11.3
Requires-Dist: importlib-resources ==5.2.0
Requires-Dist: ipykernel ==6.15.2
Requires-Dist: ipython ==7.31.1
Requires-Dist: ipython-genutils ==0.2.0
Requires-Dist: ipywidgets ==7.6.5
Requires-Dist: jedi ==0.18.1
Requires-Dist: jinja2 ==3.1.2
Requires-Dist: joblib ==1.1.0
Requires-Dist: json5 ==0.9.6
Requires-Dist: jsonschema ==4.17.3
Requires-Dist: jupyter ==1.0.0
Requires-Dist: jupyter-console ==6.6.3
Requires-Dist: jupyter-core ==4.12.0
Requires-Dist: jupyter-server ==1.24.0
Requires-Dist: jupyter-client ==7.4.9
Requires-Dist: jupyter-telemetry ==0.1.0
Requires-Dist: jupyterhub ==4.1.5
Requires-Dist: jupyterlab ==3.3.2
Requires-Dist: jupyterlab-pygments ==0.1.2
Requires-Dist: jupyterlab-server ==2.10.3
Requires-Dist: jupyterlab-widgets ==1.0.0
Requires-Dist: keras ==2.11.0
Requires-Dist: kiwisolver ==1.4.4
Requires-Dist: nbclient ==0.5.13
Requires-Dist: nbconvert ==7.6.0
Requires-Dist: nbformat ==5.7.0
Requires-Dist: nest-asyncio ==1.5.6
Requires-Dist: notebook ==6.4.13
Requires-Dist: notebook-shim ==0.2.4
Requires-Dist: numba ==0.55.1
Requires-Dist: numexpr ==2.8.4
Requires-Dist: oauthlib ==3.2.1
Requires-Dist: opt-einsum ==3.3.0
Requires-Dist: packaging ==22.0
Requires-Dist: pandas ==1.3.5
Requires-Dist: pandocfilters ==1.5.0
Requires-Dist: parso ==0.8.3
Requires-Dist: pexpect ==4.8.0
Requires-Dist: pickleshare ==0.7.5
Requires-Dist: pillow ==9.4.0
Requires-Dist: prometheus-client ==0.14.1
Requires-Dist: prompt-toolkit ==3.0.36
Requires-Dist: protobuf ==3.19.6
Requires-Dist: psutil ==5.8.0
Requires-Dist: ptyprocess ==0.7.0
Requires-Dist: py3dmol ==2.1.0
Requires-Dist: pyasn1 ==0.5.1
Requires-Dist: pyasn1-modules ==0.3.0
Requires-Dist: pycparser ==2.21
Requires-Dist: pygments ==2.10.0
Requires-Dist: pyjwt ==2.4.0
Requires-Dist: pyopenssl ==23.0.0
Requires-Dist: pyparsing ==3.1.2
Requires-Dist: pyqt ==5.15.7
Requires-Dist: pyqt5-sip ==12.11.0
Requires-Dist: pyrsistent ==0.18.0
Requires-Dist: pysocks ==1.7.1
Requires-Dist: python-dateutil ==2.8.2
Requires-Dist: python-fastjsonschema ==2.16.2
Requires-Dist: pyyaml ==6.0
Requires-Dist: pyzmq ==25.1.2
Requires-Dist: qtconsole ==5.4.4
Requires-Dist: qtpy ==2.4.1
Requires-Dist: requests ==2.28.1
Requires-Dist: rsa ==4.9
Requires-Dist: ruamel.yaml ==0.17.21
Requires-Dist: ruamel.yaml.clib ==0.2.6
Requires-Dist: scikit-learn ==1.0.2
Requires-Dist: scipy ==1.7.3
Requires-Dist: send2trash ==1.8.0
Requires-Dist: setuptools ==65.6.3
Requires-Dist: sip ==6.6.2
Requires-Dist: six ==1.16.0
Requires-Dist: sniffio ==1.2.0
Requires-Dist: soupsieve ==2.4.1
Requires-Dist: sqlalchemy ==1.4.39
Requires-Dist: tensorboard ==2.11.2
Requires-Dist: tensorboard-data-server ==0.6.1
Requires-Dist: tensorboard-plugin-wit ==1.8.1
Requires-Dist: tensorflow ==2.11.0
Requires-Dist: tensorflow-estimator ==2.11.0
Requires-Dist: tensorflow-io-gcs-filesystem ==0.34.0
Requires-Dist: termcolor ==2.3.0
Requires-Dist: terminado ==0.12.1
Requires-Dist: testpath ==0.5.0
Requires-Dist: threadpoolctl ==3.0.0
Requires-Dist: tifffile ==2021.11.2
Requires-Dist: tinycss2 ==1.2.1
Requires-Dist: toolz ==0.12.1
Requires-Dist: torch ==1.13.1
Requires-Dist: torchaudio ==0.2
Requires-Dist: torchvision ==0.2.0
Requires-Dist: tornado ==6.2
Requires-Dist: tqdm ==4.62.3
Requires-Dist: traitlets ==5.7.1
Requires-Dist: typing-extensions ==3.10.0.2
Requires-Dist: typing-extensions ==4.4.0
Requires-Dist: umap-learn ==0.5.3
Requires-Dist: urllib3 ==1.26.7
Requires-Dist: wcwidth ==0.2.5
Requires-Dist: webencodings ==0.5.1
Requires-Dist: websocket-client ==1.2.1
Requires-Dist: werkzeug ==2.2.3
Requires-Dist: wget ==3.2
Requires-Dist: widgetsnbextension ==3.5.2
Requires-Dist: wrapt ==1.16.0
Requires-Dist: zipp ==3.6.0
